pzctest/__init__.py
pzctest/test.py
peng_test-0.0.3.dist-info/LICENSE
peng_test-0.0.3.dist-info/METADATA
peng_test-0.0.3.dist-info/WHEEL
peng_test-0.0.3.dist-info/top_level.txt
peng_test-0.0.3.dist-info/RECORD
